[
  {
    "id": "vid001",
    "title": "Sporty Plugged Ride",
    "thumb": "/assets/thumbs/sporty1.jpg",
    "url": "https://manyvids.com/video/sportyplug",
    "outfit": "Sporty Suit",
    "position": ["Riding", "Doggy"],
    "accessories": ["Plug", "Vibro"],
    "mood": ["Submissive", "Breathy"]
  },
  {
    "id": "vid002",
    "title": "Latex Obedience Training",
    "thumb": "/assets/thumbs/latex1.jpg",
    "url": "https://manyvids.com/video/latextraining",
    "outfit": "Black Latex",
    "position": ["Facefuck", "Missionary"],
    "accessories": ["Collar", "Handcuffs"],
    "mood": ["Silent", "Obedient"]
  },
  {
    "id": "vid003",
    "title": "Schoolgirl Gag Reflex",
    "thumb": "/assets/thumbs/schoolgirl1.jpg",
    "url": "https://manyvids.com/video/schoolgirlgag",
    "outfit": "Schoolgirl Lingerie",
    "position": ["Facefuck"],
    "accessories": ["Gag", "Collar"],
    "mood": ["Gênée", "Excited"]
  },
  {
    "id": "vid004",
    "title": "Schoolgirl Gag Reflex",
    "thumb": "/assets/thumbs/schoolgirl1.jpg",
    "url": "https://manyvids.com/video/schoolgirlgag",
    "outfit": "Schoolgirl Lingerie",
    "position": ["Facefuck"],
    "accessories": ["Gag", "Collar"],
    "mood": ["Gênée", "Excited"]
  }
]
